LICENSE.md
MANIFEST.in
README.md
setup.cfg
setup.py
requirements/common.txt
tests/test_api.py
tonplay/__init__.py
tonplay/__version__.py
tonplay/api.py
tonplay/error.py
tonplay/lib/__init__.py
tonplay/lib/enums.py
tonplay/lib/utils.py
tonplay/methods/__init__.py
tonplay/methods/_asset.py
tonplay/methods/_auth.py
tonplay/methods/_game.py
tonplay/methods/_market.py
tonplay/methods/_ton.py
tonplay/methods/_user.py
tonplay_connector.egg-info/PKG-INFO
tonplay_connector.egg-info/SOURCES.txt
tonplay_connector.egg-info/dependency_links.txt
tonplay_connector.egg-info/requires.txt
tonplay_connector.egg-info/top_level.txt