Metadata-Version: 2.1
Name: tonplay-connector
Version: 0.0.2.1
Summary: This is a lightweight library that works as a connector to TON Play public API.
Author: TON Play
License: MIT
Keywords: TON Play,Ton Play API,Tonplay API
Requires-Python: >=3.11.1
License-File: LICENSE.md
